{"MSFT":{"mentions":105,"upvotes":2691,"rank":3,"mentionChange":1.15,"topPosts":[],"avgSentiment":0.3},"PLTR":{"mentions":80,"upvotes":400,"rank":5,"mentionChange":1.18,"topPosts":[],"avgSentiment":0},"TSLA":{"mentions":34,"upvotes":71,"rank":10,"mentionChange":4.86,"topPosts":[],"avgSentiment":0},"NOW":{"mentions":27,"upvotes":1579,"rank":14,"mentionChange":1.35,"topPosts":[],"avgSentiment":0.3},"NVDA":{"mentions":22,"upvotes":63,"rank":18,"mentionChange":2,"topPosts":[],"avgSentiment":0},"JPM":{"mentions":19,"upvotes":40,"rank":21,"mentionChange":3.17,"topPosts":[],"avgSentiment":0},"AMZN":{"mentions":18,"upvotes":62,"rank":23,"mentionChange":2.57,"topPosts":[],"avgSentiment":0},"AMD":{"mentions":17,"upvotes":35,"rank":28,"mentionChange":1.55,"topPosts":[],"avgSentiment":0},"INTC":{"mentions":16,"upvotes":53,"rank":31,"mentionChange":1.6,"topPosts":[],"avgSentiment":0},"XOM":{"mentions":9,"upvotes":18,"rank":40,"mentionChange":1.8,"topPosts":[],"avgSentiment":-0.1},"NFLX":{"mentions":6,"upvotes":26,"rank":53,"mentionChange":1.2,"topPosts":[],"avgSentiment":0},"CRM":{"mentions":6,"upvotes":26,"rank":54,"mentionChange":6,"topPosts":[],"avgSentiment":0},"MS":{"mentions":6,"upvotes":42,"rank":55,"mentionChange":0.46,"topPosts":[],"avgSentiment":0.1},"HOOD":{"mentions":6,"upvotes":58,"rank":61,"mentionChange":6,"topPosts":[],"avgSentiment":0.1},"META":{"mentions":6,"upvotes":54,"rank":62,"mentionChange":0.35,"topPosts":[],"avgSentiment":0.1},"AAPL":{"mentions":5,"upvotes":18,"rank":65,"mentionChange":1.25,"topPosts":[],"avgSentiment":0},"MA":{"mentions":5,"upvotes":9,"rank":66,"mentionChange":2.5,"topPosts":[],"avgSentiment":-0.1},"SOFI":{"mentions":5,"upvotes":24,"rank":77,"mentionChange":5,"topPosts":[],"avgSentiment":0},"AVGO":{"mentions":4,"upvotes":11,"rank":85,"mentionChange":0.8,"topPosts":[],"avgSentiment":0},"SNOW":{"mentions":4,"upvotes":12,"rank":89,"mentionChange":2,"topPosts":[],"avgSentiment":0},"LMT":{"mentions":3,"upvotes":13,"rank":96,"mentionChange":null,"topPosts":[],"avgSentiment":0},"GS":{"mentions":3,"upvotes":27,"rank":98,"mentionChange":0.5,"topPosts":[],"avgSentiment":0.1},"UNH":{"mentions":3,"upvotes":4,"rank":99,"mentionChange":0.3,"topPosts":[],"avgSentiment":-0.1},"RTX":{"mentions":3,"upvotes":11,"rank":101,"mentionChange":3,"topPosts":[],"avgSentiment":0},"JNJ":{"mentions":2,"upvotes":7,"rank":116,"mentionChange":0.2,"topPosts":[],"avgSentiment":0},"CVX":{"mentions":2,"upvotes":4,"rank":125,"mentionChange":2,"topPosts":[],"avgSentiment":-0.1},"SNAP":{"mentions":2,"upvotes":9,"rank":135,"mentionChange":0.67,"topPosts":[],"avgSentiment":0},"PANW":{"mentions":2,"upvotes":6,"rank":136,"mentionChange":2,"topPosts":[],"avgSentiment":0},"GOOGL":{"mentions":2,"upvotes":33,"rank":158,"mentionChange":1,"topPosts":[],"avgSentiment":0.3},"WMT":{"mentions":1,"upvotes":1,"rank":162,"mentionChange":null,"topPosts":[],"avgSentiment":-0.1},"PG":{"mentions":1,"upvotes":5,"rank":163,"mentionChange":1,"topPosts":[],"avgSentiment":0},"BAC":{"mentions":1,"upvotes":1,"rank":164,"mentionChange":1,"topPosts":[],"avgSentiment":-0.1},"HD":{"mentions":1,"upvotes":2,"rank":165,"mentionChange":null,"topPosts":[],"avgSentiment":-0.1},"KO":{"mentions":1,"upvotes":6,"rank":166,"mentionChange":1,"topPosts":[],"avgSentiment":0.1},"PEP":{"mentions":1,"upvotes":16,"rank":167,"mentionChange":null,"topPosts":[],"avgSentiment":0.3},"PFE":{"mentions":1,"upvotes":3,"rank":168,"mentionChange":null,"topPosts":[],"avgSentiment":0},"CSCO":{"mentions":1,"upvotes":3,"rank":169,"mentionChange":1,"topPosts":[],"avgSentiment":0},"BA":{"mentions":1,"upvotes":2,"rank":170,"mentionChange":1,"topPosts":[],"avgSentiment":-0.1},"ADBE":{"mentions":1,"upvotes":12,"rank":171,"mentionChange":0.2,"topPosts":[],"avgSentiment":0.3},"ORCL":{"mentions":1,"upvotes":18,"rank":172,"mentionChange":1,"topPosts":[],"avgSentiment":0.3},"MCD":{"mentions":1,"upvotes":14,"rank":174,"mentionChange":1,"topPosts":[],"avgSentiment":0.3},"COST":{"mentions":1,"upvotes":1,"rank":176,"mentionChange":1,"topPosts":[],"avgSentiment":-0.1},"ABT":{"mentions":1,"upvotes":4,"rank":177,"mentionChange":1,"topPosts":[],"avgSentiment":0},"LLY":{"mentions":1,"upvotes":3,"rank":181,"mentionChange":0.33,"topPosts":[],"avgSentiment":0},"TMO":{"mentions":1,"upvotes":1,"rank":182,"mentionChange":null,"topPosts":[],"avgSentiment":-0.1},"AMGN":{"mentions":1,"upvotes":1,"rank":183,"mentionChange":1,"topPosts":[],"avgSentiment":-0.1},"AMT":{"mentions":1,"upvotes":2,"rank":185,"mentionChange":null,"topPosts":[],"avgSentiment":-0.1},"AMAT":{"mentions":1,"upvotes":7,"rank":193,"mentionChange":0.2,"topPosts":[],"avgSentiment":0.1},"CAT":{"mentions":1,"upvotes":0,"rank":201,"mentionChange":1,"topPosts":[],"avgSentiment":-0.1},"COP":{"mentions":1,"upvotes":2,"rank":205,"mentionChange":null,"topPosts":[],"avgSentiment":-0.1},"DE":{"mentions":1,"upvotes":4,"rank":207,"mentionChange":1,"topPosts":[],"avgSentiment":0},"GE":{"mentions":1,"upvotes":11,"rank":213,"mentionChange":1,"topPosts":[],"avgSentiment":0.3},"INTU":{"mentions":1,"upvotes":9,"rank":217,"mentionChange":1,"topPosts":[],"avgSentiment":0.1},"LOW":{"mentions":1,"upvotes":6,"rank":225,"mentionChange":1,"topPosts":[],"avgSentiment":0.1},"NKE":{"mentions":1,"upvotes":4,"rank":231,"mentionChange":0.5,"topPosts":[],"avgSentiment":0},"QCOM":{"mentions":1,"upvotes":1,"rank":236,"mentionChange":null,"topPosts":[],"avgSentiment":-0.1},"UPS":{"mentions":1,"upvotes":1,"rank":245,"mentionChange":1,"topPosts":[],"avgSentiment":-0.1},"MRK":{"mentions":1,"upvotes":4,"rank":249,"mentionChange":1,"topPosts":[],"avgSentiment":0},"WFC":{"mentions":1,"upvotes":1,"rank":250,"mentionChange":1,"topPosts":[],"avgSentiment":-0.1},"NEE":{"mentions":1,"upvotes":1,"rank":252,"mentionChange":1,"topPosts":[],"avgSentiment":-0.1},"HON":{"mentions":1,"upvotes":5,"rank":253,"mentionChange":1,"topPosts":[],"avgSentiment":0},"ZS":{"mentions":1,"upvotes":4,"rank":278,"mentionChange":1,"topPosts":[],"avgSentiment":0},"TTD":{"mentions":1,"upvotes":1,"rank":289,"mentionChange":0.5,"topPosts":[],"avgSentiment":-0.1},"SMCI":{"mentions":1,"upvotes":1,"rank":291,"mentionChange":1,"topPosts":[],"avgSentiment":-0.1},"MDB":{"mentions":1,"upvotes":28,"rank":300,"mentionChange":1,"topPosts":[],"avgSentiment":0.3},"DDOG":{"mentions":1,"upvotes":2,"rank":310,"mentionChange":null,"topPosts":[],"avgSentiment":-0.1},"PINS":{"mentions":1,"upvotes":2,"rank":331,"mentionChange":1,"topPosts":[],"avgSentiment":-0.1},"CRWD":{"mentions":1,"upvotes":4,"rank":350,"mentionChange":1,"topPosts":[],"avgSentiment":0},"UBER":{"mentions":1,"upvotes":1,"rank":361,"mentionChange":1,"topPosts":[],"avgSentiment":-0.1},"HUBS":{"mentions":1,"upvotes":2,"rank":388,"mentionChange":1,"topPosts":[],"avgSentiment":-0.1},"NET":{"mentions":1,"upvotes":3,"rank":398,"mentionChange":0.2,"topPosts":[],"avgSentiment":0},"U":{"mentions":1,"upvotes":0,"rank":416,"mentionChange":null,"topPosts":[],"avgSentiment":-0.1},"AFRM":{"mentions":1,"upvotes":1,"rank":555,"mentionChange":1,"topPosts":[],"avgSentiment":-0.1},"PATH":{"mentions":1,"upvotes":-1,"rank":570,"mentionChange":1,"topPosts":[],"avgSentiment":-0.1},"RIVN":{"mentions":1,"upvotes":0,"rank":606,"mentionChange":1,"topPosts":[],"avgSentiment":-0.1},"ARM":{"mentions":1,"upvotes":1,"rank":689,"mentionChange":1,"topPosts":[],"avgSentiment":-0.1}}