{"MSFT":{"mentions":161,"upvotes":531,"rank":3,"mentionChange":0.65,"topPosts":[],"avgSentiment":0},"NKE":{"mentions":76,"upvotes":273,"rank":7,"mentionChange":9.5,"topPosts":[],"avgSentiment":0},"NVDA":{"mentions":75,"upvotes":229,"rank":8,"mentionChange":0.6,"topPosts":[],"avgSentiment":0},"JPM":{"mentions":59,"upvotes":3141,"rank":11,"mentionChange":1.9,"topPosts":[],"avgSentiment":0.3},"META":{"mentions":54,"upvotes":236,"rank":13,"mentionChange":0.77,"topPosts":[],"avgSentiment":0},"TSLA":{"mentions":37,"upvotes":92,"rank":19,"mentionChange":0.66,"topPosts":[],"avgSentiment":0},"AMZN":{"mentions":29,"upvotes":67,"rank":22,"mentionChange":0.78,"topPosts":[],"avgSentiment":0},"HOOD":{"mentions":25,"upvotes":171,"rank":27,"mentionChange":0.96,"topPosts":[],"avgSentiment":0.1},"GOOGL":{"mentions":20,"upvotes":42,"rank":35,"mentionChange":1.18,"topPosts":[],"avgSentiment":0},"NOW":{"mentions":18,"upvotes":433,"rank":39,"mentionChange":1,"topPosts":[],"avgSentiment":0.3},"AMD":{"mentions":15,"upvotes":161,"rank":46,"mentionChange":0.54,"topPosts":[],"avgSentiment":0.3},"SNAP":{"mentions":15,"upvotes":49,"rank":47,"mentionChange":7.5,"topPosts":[],"avgSentiment":0},"AAPL":{"mentions":14,"upvotes":28,"rank":51,"mentionChange":0.7,"topPosts":[],"avgSentiment":-0.1},"GE":{"mentions":12,"upvotes":3049,"rank":62,"mentionChange":6,"topPosts":[],"avgSentiment":0.3},"PLTR":{"mentions":12,"upvotes":26,"rank":65,"mentionChange":0.44,"topPosts":[],"avgSentiment":0},"ORCL":{"mentions":9,"upvotes":26,"rank":83,"mentionChange":0.6,"topPosts":[],"avgSentiment":0},"XOM":{"mentions":9,"upvotes":47,"rank":84,"mentionChange":0.33,"topPosts":[],"avgSentiment":0.1},"MA":{"mentions":7,"upvotes":23,"rank":102,"mentionChange":0.39,"topPosts":[],"avgSentiment":0},"UNH":{"mentions":7,"upvotes":23,"rank":106,"mentionChange":1,"topPosts":[],"avgSentiment":0},"CVX":{"mentions":7,"upvotes":72,"rank":107,"mentionChange":0.7,"topPosts":[],"avgSentiment":0.3},"SOFI":{"mentions":6,"upvotes":12,"rank":115,"mentionChange":0.46,"topPosts":[],"avgSentiment":-0.1},"ADBE":{"mentions":5,"upvotes":7,"rank":123,"mentionChange":1.25,"topPosts":[],"avgSentiment":-0.1},"PG":{"mentions":4,"upvotes":7,"rank":143,"mentionChange":4,"topPosts":[],"avgSentiment":-0.1},"NFLX":{"mentions":3,"upvotes":5,"rank":159,"mentionChange":0.75,"topPosts":[],"avgSentiment":-0.1},"LMT":{"mentions":3,"upvotes":6,"rank":160,"mentionChange":0.38,"topPosts":[],"avgSentiment":-0.1},"ARM":{"mentions":3,"upvotes":4,"rank":188,"mentionChange":1,"topPosts":[],"avgSentiment":-0.1},"INTC":{"mentions":2,"upvotes":16,"rank":194,"mentionChange":0.33,"topPosts":[],"avgSentiment":0.1},"CRM":{"mentions":2,"upvotes":3,"rank":203,"mentionChange":0.67,"topPosts":[],"avgSentiment":-0.1},"MS":{"mentions":2,"upvotes":4,"rank":205,"mentionChange":0.33,"topPosts":[],"avgSentiment":-0.1},"PATH":{"mentions":2,"upvotes":28,"rank":239,"mentionChange":2,"topPosts":[],"avgSentiment":0.3},"JNJ":{"mentions":1,"upvotes":1,"rank":257,"mentionChange":1,"topPosts":[],"avgSentiment":-0.1},"WMT":{"mentions":1,"upvotes":4,"rank":258,"mentionChange":1,"topPosts":[],"avgSentiment":0},"BAC":{"mentions":1,"upvotes":1,"rank":259,"mentionChange":0.33,"topPosts":[],"avgSentiment":-0.1},"HD":{"mentions":1,"upvotes":163,"rank":260,"mentionChange":1,"topPosts":[],"avgSentiment":0.3},"KO":{"mentions":1,"upvotes":1,"rank":261,"mentionChange":0.33,"topPosts":[],"avgSentiment":-0.1},"DIS":{"mentions":1,"upvotes":32,"rank":262,"mentionChange":0.25,"topPosts":[],"avgSentiment":0.3},"PEP":{"mentions":1,"upvotes":41,"rank":263,"mentionChange":1,"topPosts":[],"avgSentiment":0.3},"PFE":{"mentions":1,"upvotes":2,"rank":264,"mentionChange":0.33,"topPosts":[],"avgSentiment":-0.1},"CSCO":{"mentions":1,"upvotes":2,"rank":265,"mentionChange":null,"topPosts":[],"avgSentiment":-0.1},"BA":{"mentions":1,"upvotes":2,"rank":266,"mentionChange":1,"topPosts":[],"avgSentiment":-0.1},"MCD":{"mentions":1,"upvotes":3,"rank":268,"mentionChange":1,"topPosts":[],"avgSentiment":0},"COST":{"mentions":1,"upvotes":1,"rank":269,"mentionChange":0.33,"topPosts":[],"avgSentiment":-0.1},"LLY":{"mentions":1,"upvotes":3,"rank":272,"mentionChange":0.33,"topPosts":[],"avgSentiment":0},"AVGO":{"mentions":1,"upvotes":6,"rank":273,"mentionChange":0.13,"topPosts":[],"avgSentiment":0.1},"AMT":{"mentions":1,"upvotes":32,"rank":275,"mentionChange":null,"topPosts":[],"avgSentiment":0.3},"AXP":{"mentions":1,"upvotes":23,"rank":281,"mentionChange":1,"topPosts":[],"avgSentiment":0.3},"AMAT":{"mentions":1,"upvotes":2,"rank":284,"mentionChange":1,"topPosts":[],"avgSentiment":-0.1},"BLK":{"mentions":1,"upvotes":1,"rank":288,"mentionChange":null,"topPosts":[],"avgSentiment":-0.1},"CAT":{"mentions":1,"upvotes":1,"rank":293,"mentionChange":1,"topPosts":[],"avgSentiment":-0.1},"COP":{"mentions":1,"upvotes":0,"rank":301,"mentionChange":1,"topPosts":[],"avgSentiment":-0.1},"DE":{"mentions":1,"upvotes":0,"rank":303,"mentionChange":1,"topPosts":[],"avgSentiment":-0.1},"EOG":{"mentions":1,"upvotes":0,"rank":304,"mentionChange":null,"topPosts":[],"avgSentiment":-0.1},"GS":{"mentions":1,"upvotes":2,"rank":313,"mentionChange":0.5,"topPosts":[],"avgSentiment":-0.1},"INTU":{"mentions":1,"upvotes":4,"rank":317,"mentionChange":0.5,"topPosts":[],"avgSentiment":0},"LOW":{"mentions":1,"upvotes":3,"rank":325,"mentionChange":1,"topPosts":[],"avgSentiment":0},"QCOM":{"mentions":1,"upvotes":4,"rank":342,"mentionChange":1,"topPosts":[],"avgSentiment":0},"SBUX":{"mentions":1,"upvotes":0,"rank":347,"mentionChange":1,"topPosts":[],"avgSentiment":-0.1},"UPS":{"mentions":1,"upvotes":2,"rank":352,"mentionChange":0.5,"topPosts":[],"avgSentiment":-0.1},"VZ":{"mentions":1,"upvotes":1,"rank":356,"mentionChange":1,"topPosts":[],"avgSentiment":-0.1},"MRK":{"mentions":1,"upvotes":1,"rank":357,"mentionChange":null,"topPosts":[],"avgSentiment":-0.1},"NEE":{"mentions":1,"upvotes":1,"rank":358,"mentionChange":1,"topPosts":[],"avgSentiment":-0.1},"HON":{"mentions":1,"upvotes":2,"rank":359,"mentionChange":1,"topPosts":[],"avgSentiment":-0.1},"DUK":{"mentions":1,"upvotes":2,"rank":366,"mentionChange":1,"topPosts":[],"avgSentiment":-0.1},"ZS":{"mentions":1,"upvotes":1,"rank":392,"mentionChange":1,"topPosts":[],"avgSentiment":-0.1},"TTD":{"mentions":1,"upvotes":1,"rank":401,"mentionChange":1,"topPosts":[],"avgSentiment":-0.1},"SMCI":{"mentions":1,"upvotes":4,"rank":405,"mentionChange":0.14,"topPosts":[],"avgSentiment":0},"DDOG":{"mentions":1,"upvotes":1,"rank":435,"mentionChange":1,"topPosts":[],"avgSentiment":-0.1},"PINS":{"mentions":1,"upvotes":3,"rank":469,"mentionChange":1,"topPosts":[],"avgSentiment":0},"CRWD":{"mentions":1,"upvotes":1,"rank":485,"mentionChange":0.33,"topPosts":[],"avgSentiment":-0.1},"UBER":{"mentions":1,"upvotes":4,"rank":501,"mentionChange":0.5,"topPosts":[],"avgSentiment":0},"SHOP":{"mentions":1,"upvotes":1,"rank":516,"mentionChange":null,"topPosts":[],"avgSentiment":-0.1},"RTX":{"mentions":1,"upvotes":5,"rank":523,"mentionChange":0.33,"topPosts":[],"avgSentiment":0},"PANW":{"mentions":1,"upvotes":5,"rank":527,"mentionChange":0.2,"topPosts":[],"avgSentiment":0},"NET":{"mentions":1,"upvotes":69,"rank":558,"mentionChange":1,"topPosts":[],"avgSentiment":0.3},"BILL":{"mentions":1,"upvotes":12,"rank":568,"mentionChange":1,"topPosts":[],"avgSentiment":0.3},"SNOW":{"mentions":1,"upvotes":2,"rank":579,"mentionChange":1,"topPosts":[],"avgSentiment":-0.1},"COIN":{"mentions":1,"upvotes":1,"rank":777,"mentionChange":null,"topPosts":[],"avgSentiment":-0.1},"RIVN":{"mentions":1,"upvotes":0,"rank":862,"mentionChange":1,"topPosts":[],"avgSentiment":-0.1}}