{"NVDA":{"mentions":104,"upvotes":4728,"rank":3,"mentionChange":1.25,"topPosts":[],"avgSentiment":0.3},"ORCL":{"mentions":82,"upvotes":191,"rank":6,"mentionChange":3.57,"topPosts":[],"avgSentiment":0},"MSFT":{"mentions":73,"upvotes":148,"rank":7,"mentionChange":2.35,"topPosts":[],"avgSentiment":0},"TSLA":{"mentions":56,"upvotes":149,"rank":10,"mentionChange":1,"topPosts":[],"avgSentiment":0},"AMD":{"mentions":29,"upvotes":4363,"rank":21,"mentionChange":2.23,"topPosts":[],"avgSentiment":0.3},"META":{"mentions":20,"upvotes":4300,"rank":33,"mentionChange":1.67,"topPosts":[],"avgSentiment":0.3},"WMT":{"mentions":19,"upvotes":334,"rank":34,"mentionChange":19,"topPosts":[],"avgSentiment":0.3},"JPM":{"mentions":16,"upvotes":548,"rank":39,"mentionChange":2.67,"topPosts":[],"avgSentiment":0.3},"HOOD":{"mentions":16,"upvotes":51,"rank":40,"mentionChange":1.14,"topPosts":[],"avgSentiment":0},"RIVN":{"mentions":15,"upvotes":36,"rank":42,"mentionChange":1.67,"topPosts":[],"avgSentiment":0},"NOW":{"mentions":14,"upvotes":31,"rank":45,"mentionChange":1.08,"topPosts":[],"avgSentiment":0},"RTX":{"mentions":12,"upvotes":34,"rank":54,"mentionChange":0.63,"topPosts":[],"avgSentiment":0},"GOOGL":{"mentions":12,"upvotes":31,"rank":55,"mentionChange":0.71,"topPosts":[],"avgSentiment":0},"AVGO":{"mentions":11,"upvotes":25,"rank":56,"mentionChange":0.85,"topPosts":[],"avgSentiment":0},"CRWD":{"mentions":11,"upvotes":19,"rank":58,"mentionChange":null,"topPosts":[],"avgSentiment":-0.1},"AAPL":{"mentions":10,"upvotes":45,"rank":62,"mentionChange":1.25,"topPosts":[],"avgSentiment":0},"AMZN":{"mentions":10,"upvotes":23,"rank":63,"mentionChange":0.53,"topPosts":[],"avgSentiment":0},"DE":{"mentions":10,"upvotes":35,"rank":64,"mentionChange":10,"topPosts":[],"avgSentiment":0},"XOM":{"mentions":10,"upvotes":20,"rank":66,"mentionChange":0.34,"topPosts":[],"avgSentiment":-0.1},"CRM":{"mentions":10,"upvotes":0,"rank":67,"mentionChange":3.33,"topPosts":[],"avgSentiment":-0.1},"NET":{"mentions":10,"upvotes":27,"rank":71,"mentionChange":null,"topPosts":[],"avgSentiment":0},"PLTR":{"mentions":10,"upvotes":118,"rank":72,"mentionChange":0.4,"topPosts":[],"avgSentiment":0.3},"NFLX":{"mentions":6,"upvotes":23,"rank":99,"mentionChange":0.75,"topPosts":[],"avgSentiment":0},"CAT":{"mentions":6,"upvotes":9,"rank":100,"mentionChange":3,"topPosts":[],"avgSentiment":-0.1},"SOFI":{"mentions":6,"upvotes":43,"rank":106,"mentionChange":2,"topPosts":[],"avgSentiment":0.1},"PATH":{"mentions":6,"upvotes":39,"rank":107,"mentionChange":1.2,"topPosts":[],"avgSentiment":0.1},"MA":{"mentions":5,"upvotes":20,"rank":113,"mentionChange":0.71,"topPosts":[],"avgSentiment":0},"MCD":{"mentions":5,"upvotes":21,"rank":114,"mentionChange":5,"topPosts":[],"avgSentiment":0},"BA":{"mentions":4,"upvotes":6,"rank":130,"mentionChange":1.33,"topPosts":[],"avgSentiment":-0.1},"LMT":{"mentions":4,"upvotes":10,"rank":131,"mentionChange":0.33,"topPosts":[],"avgSentiment":0},"INTU":{"mentions":4,"upvotes":4,"rank":137,"mentionChange":1.33,"topPosts":[],"avgSentiment":-0.1},"CVX":{"mentions":4,"upvotes":9,"rank":138,"mentionChange":0.8,"topPosts":[],"avgSentiment":0},"KO":{"mentions":3,"upvotes":6,"rank":159,"mentionChange":3,"topPosts":[],"avgSentiment":-0.1},"COST":{"mentions":3,"upvotes":34,"rank":161,"mentionChange":3,"topPosts":[],"avgSentiment":0.3},"TTD":{"mentions":3,"upvotes":5,"rank":167,"mentionChange":3,"topPosts":[],"avgSentiment":-0.1},"SMCI":{"mentions":3,"upvotes":4,"rank":168,"mentionChange":3,"topPosts":[],"avgSentiment":-0.1},"BAC":{"mentions":2,"upvotes":6,"rank":200,"mentionChange":2,"topPosts":[],"avgSentiment":0},"HD":{"mentions":2,"upvotes":4,"rank":201,"mentionChange":2,"topPosts":[],"avgSentiment":-0.1},"LLY":{"mentions":2,"upvotes":13,"rank":202,"mentionChange":2,"topPosts":[],"avgSentiment":0.1},"AMT":{"mentions":2,"upvotes":3,"rank":204,"mentionChange":null,"topPosts":[],"avgSentiment":-0.1},"AXP":{"mentions":2,"upvotes":5,"rank":206,"mentionChange":null,"topPosts":[],"avgSentiment":0},"UPS":{"mentions":2,"upvotes":11,"rank":210,"mentionChange":1,"topPosts":[],"avgSentiment":0.1},"ZS":{"mentions":2,"upvotes":3,"rank":213,"mentionChange":null,"topPosts":[],"avgSentiment":-0.1},"JNJ":{"mentions":1,"upvotes":2,"rank":259,"mentionChange":1,"topPosts":[],"avgSentiment":-0.1},"PG":{"mentions":1,"upvotes":1,"rank":260,"mentionChange":1,"topPosts":[],"avgSentiment":-0.1},"INTC":{"mentions":1,"upvotes":3,"rank":261,"mentionChange":1,"topPosts":[],"avgSentiment":0},"PFE":{"mentions":1,"upvotes":1,"rank":262,"mentionChange":1,"topPosts":[],"avgSentiment":-0.1},"CSCO":{"mentions":1,"upvotes":3,"rank":263,"mentionChange":1,"topPosts":[],"avgSentiment":0},"ADBE":{"mentions":1,"upvotes":8,"rank":264,"mentionChange":0.5,"topPosts":[],"avgSentiment":0.1},"ABBV":{"mentions":1,"upvotes":2,"rank":266,"mentionChange":1,"topPosts":[],"avgSentiment":-0.1},"AMGN":{"mentions":1,"upvotes":1,"rank":268,"mentionChange":1,"topPosts":[],"avgSentiment":-0.1},"AMAT":{"mentions":1,"upvotes":1,"rank":280,"mentionChange":0.25,"topPosts":[],"avgSentiment":-0.1},"BLK":{"mentions":1,"upvotes":4,"rank":284,"mentionChange":1,"topPosts":[],"avgSentiment":0},"SCHW":{"mentions":1,"upvotes":2,"rank":290,"mentionChange":1,"topPosts":[],"avgSentiment":-0.1},"COP":{"mentions":1,"upvotes":221,"rank":293,"mentionChange":0.5,"topPosts":[],"avgSentiment":0.3},"GE":{"mentions":1,"upvotes":2,"rank":309,"mentionChange":1,"topPosts":[],"avgSentiment":-0.1},"GILD":{"mentions":1,"upvotes":2,"rank":312,"mentionChange":1,"topPosts":[],"avgSentiment":-0.1},"GS":{"mentions":1,"upvotes":1,"rank":313,"mentionChange":1,"topPosts":[],"avgSentiment":-0.1},"LOW":{"mentions":1,"upvotes":3,"rank":328,"mentionChange":1,"topPosts":[],"avgSentiment":0},"NKE":{"mentions":1,"upvotes":2,"rank":336,"mentionChange":1,"topPosts":[],"avgSentiment":-0.1},"QCOM":{"mentions":1,"upvotes":1,"rank":344,"mentionChange":1,"topPosts":[],"avgSentiment":-0.1},"SLB":{"mentions":1,"upvotes":2,"rank":347,"mentionChange":0.33,"topPosts":[],"avgSentiment":-0.1},"SBUX":{"mentions":1,"upvotes":9,"rank":349,"mentionChange":null,"topPosts":[],"avgSentiment":0.1},"UNH":{"mentions":1,"upvotes":6,"rank":358,"mentionChange":0.14,"topPosts":[],"avgSentiment":0.1},"VZ":{"mentions":1,"upvotes":2,"rank":359,"mentionChange":1,"topPosts":[],"avgSentiment":-0.1},"WFC":{"mentions":1,"upvotes":4,"rank":360,"mentionChange":1,"topPosts":[],"avgSentiment":0},"HON":{"mentions":1,"upvotes":4,"rank":361,"mentionChange":null,"topPosts":[],"avgSentiment":0},"MS":{"mentions":1,"upvotes":0,"rank":379,"mentionChange":1,"topPosts":[],"avgSentiment":-0.1},"DDOG":{"mentions":1,"upvotes":1,"rank":437,"mentionChange":1,"topPosts":[],"avgSentiment":-0.1},"PINS":{"mentions":1,"upvotes":4,"rank":477,"mentionChange":0.33,"topPosts":[],"avgSentiment":0},"UBER":{"mentions":1,"upvotes":1,"rank":510,"mentionChange":0.5,"topPosts":[],"avgSentiment":-0.1},"SNAP":{"mentions":1,"upvotes":4,"rank":518,"mentionChange":1,"topPosts":[],"avgSentiment":0},"PANW":{"mentions":1,"upvotes":6,"rank":533,"mentionChange":1,"topPosts":[],"avgSentiment":0.1},"SNOW":{"mentions":1,"upvotes":8,"rank":593,"mentionChange":null,"topPosts":[],"avgSentiment":0.1},"LCID":{"mentions":1,"upvotes":1,"rank":808,"mentionChange":0.5,"topPosts":[],"avgSentiment":-0.1},"ARM":{"mentions":1,"upvotes":2,"rank":965,"mentionChange":1,"topPosts":[],"avgSentiment":-0.1}}